dso/__init__.py
dso/client.py
dso/factory.py
dso/version.py
dso/java/caffeine-2.8.4.jar
dso/java/commons-lang3-3.6.jar
dso/java/dso-client-2.0.jar
dso/java/dso-core-2.0.jar
dso/java/dso-python-2.0.jar
dso/java/ecj-4.4.2.jar
dso/java/gson-2.8.5.jar
dso/java/guava-18.0.jar
dso/java/infinispan-client-hotrod-11.0.4.Final.jar
dso/java/infinispan-commons-11.0.4.Final.jar
dso/java/java-uuid-generator-3.1.3.jar
dso/java/javassist-3.23.1-GA.jar
dso/java/javax.persistence-api-2.2.jar
dso/java/jboss-logging-3.4.1.Final.jar
dso/java/jboss-transaction-api_1.2_spec-1.1.1.Final.jar
dso/java/lambda-from-string-1.6.jar
dso/java/log4j-1.2.13.jar
dso/java/netty-buffer-4.1.51.Final.jar
dso/java/netty-codec-4.1.51.Final.jar
dso/java/netty-common-4.1.51.Final.jar
dso/java/netty-handler-4.1.51.Final.jar
dso/java/netty-resolver-4.1.51.Final.jar
dso/java/netty-transport-4.1.51.Final.jar
dso/java/netty-transport-native-epoll-4.1.51.Final-linux-x86_64.jar
dso/java/netty-transport-native-unix-common-4.1.51.Final.jar
dso/java/picocli-4.0.4.jar
dso/java/protostream-4.3.4.Final.jar
dso/java/reactive-streams-1.0.3.jar
dso/java/reflections-0.9.11.jar
dso/java/rxjava-3.0.4.jar
dso/java/wildfly-common-1.5.4.Final.jar
dso/java/wildfly-elytron-1.12.1.Final.jar
dso/java/wildfly-elytron-asn1-1.12.1.Final.jar
dso/java/wildfly-elytron-audit-1.12.1.Final.jar
dso/java/wildfly-elytron-auth-1.12.1.Final.jar
dso/java/wildfly-elytron-auth-server-1.12.1.Final.jar
dso/java/wildfly-elytron-auth-server-deprecated-1.12.1.Final.jar
dso/java/wildfly-elytron-auth-server-http-1.12.1.Final.jar
dso/java/wildfly-elytron-auth-server-sasl-1.12.1.Final.jar
dso/java/wildfly-elytron-auth-util-1.12.1.Final.jar
dso/java/wildfly-elytron-base-1.12.1.Final.jar
dso/java/wildfly-elytron-client-1.12.1.Final.jar
dso/java/wildfly-elytron-credential-1.12.1.Final.jar
dso/java/wildfly-elytron-credential-source-deprecated-1.12.1.Final.jar
dso/java/wildfly-elytron-credential-source-impl-1.12.1.Final.jar
dso-0.0.5.dist-info/METADATA
dso-0.0.5.dist-info/WHEEL
dso-0.0.5.dist-info/top_level.txt
dso-0.0.5.dist-info/RECORD
