Metadata-Version: 2.1
Name: dso
Version: 0.0.5
Summary: Python bindings for the DSO datastore
Home-page: https://github.com/crucial-project/dso
Author: Pierre Sutra
Author-email: pierre.sutra@telecom-sudparis.eu
License: UNKNOWN
Platform: UNKNOWN
Classifier: Development Status :: 2 - Pre-Alpha
Classifier: Topic :: Utilities
Classifier: License :: OSI Approved :: Apache Software License
Requires-Python: >=3.6
Requires-Dist: JPype1
